<?xml version="1.0" encoding="utf-8"?>
<EntityRelationships>
  <EntityRelationship Name="account_master_account" unmodified="1" />
  <EntityRelationship Name="account_originating_lead" unmodified="1" />
  <EntityRelationship Name="account_parent_account" unmodified="1" />
  <EntityRelationship Name="account_primary_contact" unmodified="1" />
  <EntityRelationship Name="business_unit_accounts" unmodified="1" />
  <EntityRelationship Name="business_unit_contacts" unmodified="1" />
  <EntityRelationship Name="business_unit_incidents" unmodified="1" />
  <EntityRelationship Name="business_unit_new_nacecode" />
  <EntityRelationship Name="business_unit_new_supportticket" />
  <EntityRelationship Name="contact_as_primary_contact" unmodified="1" />
  <EntityRelationship Name="contact_as_responsible_contact" unmodified="1" />
  <EntityRelationship Name="contact_customer_accounts" unmodified="1" />
  <EntityRelationship Name="contact_customer_contacts" unmodified="1" />
  <EntityRelationship Name="contact_master_contact" unmodified="1" />
  <EntityRelationship Name="contact_originating_lead" unmodified="1" />
  <EntityRelationship Name="contact_owning_user" unmodified="1" />
  <EntityRelationship Name="contract_cases" unmodified="1" />
  <EntityRelationship Name="contract_detail_cases" unmodified="1" />
  <EntityRelationship Name="entitlement_cases" unmodified="1" />
  <EntityRelationship Name="equipment_accounts" unmodified="1" />
  <EntityRelationship Name="equipment_contacts" unmodified="1" />
  <EntityRelationship Name="incident_customer_accounts" unmodified="1" />
  <EntityRelationship Name="incident_customer_contacts" unmodified="1" />
  <EntityRelationship Name="incident_existingcase" unmodified="1" />
  <EntityRelationship Name="incident_master_incident" unmodified="1" />
  <EntityRelationship Name="incident_parent_incident" unmodified="1" />
  <EntityRelationship Name="kbarticle_incidents" unmodified="1" />
  <EntityRelationship Name="KnowledgeBaseRecord_Incident" unmodified="1" />
  <EntityRelationship Name="listaccount_association" unmodified="1" />
  <EntityRelationship Name="listcontact_association" unmodified="1" />
  <EntityRelationship Name="lk_accountbase_createdby" unmodified="1" />
  <EntityRelationship Name="lk_accountbase_modifiedby" unmodified="1" />
  <EntityRelationship Name="lk_contactbase_createdby" unmodified="1" />
  <EntityRelationship Name="lk_contactbase_modifiedby" unmodified="1" />
  <EntityRelationship Name="lk_externalparty_account_createdby" unmodified="1" />
  <EntityRelationship Name="lk_externalparty_account_modifiedby" unmodified="1" />
  <EntityRelationship Name="lk_externalparty_contact_createdby" unmodified="1" />
  <EntityRelationship Name="lk_externalparty_contact_modifiedby" unmodified="1" />
  <EntityRelationship Name="lk_externalparty_incident_createdby" unmodified="1" />
  <EntityRelationship Name="lk_externalparty_incident_modifiedby" unmodified="1" />
  <EntityRelationship Name="lk_incident_ChildIncidentCount" unmodified="1" />
  <EntityRelationship Name="lk_incidentbase_createdby" unmodified="1" />
  <EntityRelationship Name="lk_incidentbase_modifiedby" unmodified="1" />
  <EntityRelationship Name="lk_new_nacecode_createdby" />
  <EntityRelationship Name="lk_new_nacecode_modifiedby" />
  <EntityRelationship Name="lk_new_supportticket_createdby" />
  <EntityRelationship Name="lk_new_supportticket_modifiedby" />
  <EntityRelationship Name="manualsla_account" unmodified="1" />
  <EntityRelationship Name="manualsla_cases" unmodified="1" />
  <EntityRelationship Name="manualsla_contact" unmodified="1" />
  <EntityRelationship Name="new_account_new_supportticket" />
  <EntityRelationship Name="new_new_nacecode_account" />
  <EntityRelationship Name="owner_accounts" unmodified="1" />
  <EntityRelationship Name="owner_contacts" unmodified="1" />
  <EntityRelationship Name="owner_incidents" unmodified="1" />
  <EntityRelationship Name="owner_new_nacecode" />
  <EntityRelationship Name="owner_new_supportticket" />
  <EntityRelationship Name="price_level_accounts" unmodified="1" />
  <EntityRelationship Name="price_level_contacts" unmodified="1" />
  <EntityRelationship Name="product_incidents" unmodified="1" />
  <EntityRelationship Name="service_accounts" unmodified="1" />
  <EntityRelationship Name="service_contacts" unmodified="1" />
  <EntityRelationship Name="sla_account" unmodified="1" />
  <EntityRelationship Name="sla_cases" unmodified="1" />
  <EntityRelationship Name="sla_contact" unmodified="1" />
  <EntityRelationship Name="slakpiinstance_incident_firstresponsebykpi" unmodified="1" />
  <EntityRelationship Name="slakpiinstance_incident_resolvebykpi" unmodified="1" />
  <EntityRelationship Name="socialprofile_cases" unmodified="1" />
  <EntityRelationship Name="subject_incidents" unmodified="1" />
  <EntityRelationship Name="system_user_accounts" unmodified="1" />
  <EntityRelationship Name="system_user_contacts" unmodified="1" />
  <EntityRelationship Name="system_user_incidents" unmodified="1" />
  <EntityRelationship Name="team_accounts" unmodified="1" />
  <EntityRelationship Name="team_contacts" unmodified="1" />
  <EntityRelationship Name="team_incidents" unmodified="1" />
  <EntityRelationship Name="team_new_nacecode" />
  <EntityRelationship Name="team_new_supportticket" />
  <EntityRelationship Name="territory_accounts" unmodified="1" />
  <EntityRelationship Name="transactioncurrency_account" unmodified="1" />
  <EntityRelationship Name="transactioncurrency_contact" unmodified="1" />
  <EntityRelationship Name="user_accounts" unmodified="1" />
  <EntityRelationship Name="user_new_nacecode" />
  <EntityRelationship Name="user_new_supportticket" />
</EntityRelationships>